uniquePicker/__init__.py
uniquePicker/core.py
unique_picker-0.0.2.dist-info/LICENSE
unique_picker-0.0.2.dist-info/METADATA
unique_picker-0.0.2.dist-info/WHEEL
unique_picker-0.0.2.dist-info/top_level.txt
unique_picker-0.0.2.dist-info/RECORD
