Metadata-Version: 2.1
Name: unique-picker
Version: 0.0.2
Summary: A package for unique random selection
Home-page: https://github.com/yourusername/unique-picker
Author: Siraj Dal
Author-email: write2siraj@gmail.com
Classifier: Programming Language :: Python :: 3
Classifier: License :: OSI Approved :: MIT License
Classifier: Operating System :: OS Independent
Requires-Python: >=3.6
License-File: LICENSE
